[
  {
    "objectID": "0c76a1652600087822049d99a4cab38c",
    "platform_id": "hmall",
    "datetime_start": "2607181600",
    "product_cnt": 47,
    "visit_cnt": null,
    "sales_cnt": null,
    "sales_amt": null,
    "title": "[현명쇼] 프라다 버킷백 10만▼ 타임딜",
    "cid": 50000167
  },
  {
    "objectID": "059811eff64ff437f72a6c7d6f37cc7c",
    "platform_id": "naver",
    "datetime_start": "2607181500",
    "product_cnt": 30,
    "visit_cnt": null,
    "sales_cnt": null,
    "sales_amt": null,
    "title": "[Ai Live] LG그램 프로 & 그램북 노트북 14/15/16/17형",
    "cid": 50000151
  },
  {
    "objectID": "1090a635663a3c987560a3252452b009",
    "platform_id": "naver",
    "datetime_start": "2607181559",
    "product_cnt": 38,
    "visit_cnt": null,
    "sales_cnt": null,
    "sales_amt": null,
    "title": "Live추가적립💚 LG가전으로 거실에서 주방까지🏠",
    "cid": 50000210
  },
  {
    "objectID": "cc8509b088e1ce4aea6a44ebfc95e299",
    "platform_id": "naver",
    "datetime_start": "2607181600",
    "product_cnt": 52,
    "visit_cnt": null,
    "sales_cnt": null,
    "sales_amt": null,
    "title": "[AI]⭐삼성 청소기, 에어컨⭐ 삼성이 선물하는 스마트 라이프",
    "cid": 50000208
  },
  {
    "objectID": "ec35c0627f6cacb1088d66fed5a62d8a",
    "platform_id": "naver",
    "datetime_start": "2607181600",
    "product_cnt": 46,
    "visit_cnt": null,
    "sales_cnt": null,
    "sales_amt": null,
    "title": "💥삼성 에어컨 냉장고 김치냉장고 키친핏 세트 Live사은품🎁[AI]",
    "cid": 50000213
  },
  {
    "objectID": "ad32dc36a6ae01898c7f1373d4ccb7b4",
    "platform_id": "cjonstyle",
    "datetime_start": "2607181600",
    "product_cnt": 60,
    "visit_cnt": null,
    "sales_cnt": null,
    "sales_amt": null,
    "title": "다시보는 맘만하니💙삼익가구 베이비장, 리클라이너 등🛋️",
    "cid": 50000105
  },
  {
    "objectID": "54d8ee0e1babcc7ad5eb60bc01235728",
    "platform_id": "naver",
    "datetime_start": "2607181600",
    "product_cnt": 18,
    "visit_cnt": null,
    "sales_cnt": null,
    "sales_amt": null,
    "title": "[AI라이브] 무더운여름 캐리어 가전 에어컨 & 제습기 라이브 혜택",
    "cid": 50000212
  },
  {
    "objectID": "535db514728ae73a1bd751c71b3fa3f3",
    "platform_id": "naver",
    "datetime_start": "2607181559",
    "product_cnt": 18,
    "visit_cnt": null,
    "sales_cnt": null,
    "sales_amt": null,
    "title": "LG그램 36% 할인! 한정재고 윈도우 or 인치 업그레이드 혜택🎁",
    "cid": 50000151
  },
  {
    "objectID": "32aaa78b9f38af634b402858e78daf4d",
    "platform_id": "naver",
    "datetime_start": "2607181602",
    "product_cnt": 40,
    "visit_cnt": null,
    "sales_cnt": null,
    "sales_amt": null,
    "title": "[AI라이브] 🏡TV,사운드바,공청기, 오늘 다솜에서 가전 다품목!",
    "cid": 50000212
  },
  {
    "objectID": "9cb1c45bd4fca3f9ce90d18c750eeb86",
    "platform_id": "gsshop",
    "datetime_start": "2607181600",
    "product_cnt": 4,
    "visit_cnt": null,
    "sales_cnt": null,
    "sales_amt": null,
    "title": "[쿠쿠] 사일런스 어반 특가! 전고객 스텐냄비 사은품",
    "cid": 50000212
  },
  {
    "objectID": "9d8bf8e5404fcbc7a4843332b7f21a6c",
    "platform_id": "naver",
    "datetime_start": "2607181500",
    "product_cnt": 30,
    "visit_cnt": null,
    "sales_cnt": null,
    "sales_amt": null,
    "title": "[AI라이브] 삼성 가전 ☘️☘ 세탁기 건조기 콤보",
    "cid": 50000210
  },
  {
    "objectID": "ac09a9a384cd15d35fc9658f3ae776d7",
    "platform_id": "naver",
    "datetime_start": "2607181559",
    "product_cnt": 32,
    "visit_cnt": null,
    "sales_cnt": null,
    "sales_amt": null,
    "title": "🎉 주말 인기 LG가전 총집합 LIVE",
    "cid": 50000210
  },
  {
    "objectID": "552bd8ade938ecb4a3301fe3a3be1999",
    "platform_id": "naver",
    "datetime_start": "2607181608",
    "product_cnt": 14,
    "visit_cnt": null,
    "sales_cnt": null,
    "sales_amt": null,
    "title": "삼성 외장하드 특가 라이브✨고용량 슬림한 디자인",
    "cid": 50000096
  },
  {
    "objectID": "bafc54c595ab1434bf3ecb3030d3fc1d",
    "platform_id": "naver",
    "datetime_start": "2607181559",
    "product_cnt": 30,
    "visit_cnt": null,
    "sales_cnt": null,
    "sales_amt": null,
    "title": "[7/18] 하만카돈 X JBL 스피커 이어폰 썸머 이벤트",
    "cid": 50000095
  },
  {
    "objectID": "1de9108eba080325cf3e41ec1c495a2e",
    "platform_id": "naver",
    "datetime_start": "2607181531",
    "product_cnt": 69,
    "visit_cnt": null,
    "sales_cnt": null,
    "sales_amt": null,
    "title": "☘️할인 혜택 갤럭시 워치8 클래식 핏3 스마트싱스 충전기",
    "cid": 50000205
  }
]
